pyseventeentrack/__init__.py
pyseventeentrack/client.py
pyseventeentrack/encrypt.py
pyseventeentrack/errors.py
pyseventeentrack/package.py
pyseventeentrack/profile.py
pyseventeentrack/track.py
pyseventeentrack-1.1.1.dist-info/AUTHORS.md
pyseventeentrack-1.1.1.dist-info/LICENSE
pyseventeentrack-1.1.1.dist-info/METADATA
pyseventeentrack-1.1.1.dist-info/WHEEL
pyseventeentrack-1.1.1.dist-info/RECORD
