Metadata-Version: 2.3
Name: pyseventeentrack
Version: 1.1.1
Summary: A Simple Python API for 17track.net
License: MIT
Author: Shai Ungar
Author-email: shaiungar@gmail.com
Requires-Python: >=3.9.0,<4.0.0
Classifier: License :: OSI Approved :: MIT License
Classifier: Programming Language :: Python
Classifier: Programming Language :: Python :: 3
Classifier: Programming Language :: Python :: 3.9
Classifier: Programming Language :: Python :: 3.10
Classifier: Programming Language :: Python :: 3.11
Classifier: Programming Language :: Python :: 3.12
Classifier: Programming Language :: Python :: 3.13
Classifier: Programming Language :: Python :: Implementation :: CPython
Classifier: Programming Language :: Python :: Implementation :: PyPy
Requires-Dist: aiohttp (>=3.9.5)
Requires-Dist: attrs (>=19.3)
Requires-Dist: cryptography (>=45.0.3)
Requires-Dist: pytz (>=2021.1)
Project-URL: Repository, https://github.com/shaiu/pyseventeentrack
